{
  "start": {
    "id": "start",
    "text": "'...씨!, 야간에 1시간만 더 해줄 수 있어?' \n그날은 알바를 시작한 지 딱 5일째 되는 평범한 금요일이었다. \n'당연히 야근 수당 챙겨줄 거고, 원래 하시던 분이 퇴사하시는 바람에...' \n일은 간단했다. \n창고정리 \n인쇄 제조업이라 창고에는 팔레트에 쌓인 지류가 층층이 천장에 닿을 만큼 가득 차 있었다. \n그걸 사이즈별로 정리하면 되는 일이었다.",
    "background": "./assets/party.jpg",
    "choices": [
      { "text": "수락한다", "nextId": "T1" },
      { "text": "머뭇거린다", "nextId": "T1" }
    ]
  },
  "T1": {
    "id": "T1",
    "text": "'야간조가 올 때까지만 하면 돼' \n'크게 어려울 건 없어' \n'어차피 야간에 인쇄기 돌리면 또 난장판 되는 건 똑 같으니까' \n'양이 적은 것만 추려서 앞에다가 빼놓고' \n'인쇄부 사람들은 꼭 꺼내서 쓰기 편한 것만 쓰더라고' \n이어지는 관리자의 푸념이었다. \n자잘하게 남는 지류를 모아서 수량을 맞추기보다는 애초에 새 것을 써버린다나 \n그래서 창고가 이 모양이다. \n여기저기에 쓰다가 남은 지류가 올려진 팔레트가 애처롭게 쳐다보는 듯 했다.",
    "choices": [
      { "text": "지게차로 걸어간다", "nextId": "T2" },
      { "text": "한숨부터 쉰다", "nextId": "T2" }
    ]
  },
  "T2": {
    "id": "T2",
    "text": "지게차에 시동이 걸렸다. \n창고에서 쓰는 작은 거인이 미끄러지듯 앞으로 움직였다. \n전기로 구동하는 입식인데, 정식으로 교육이수를 받았을리 만무하고, \n그냥 현장에서 일하는 누군가에게 속성으로 배웠다. \n얼마간의 시간이 흘렀고 \n지게차가 움직일 때마다 흩어져 있던 팔레트들이 제법 모였다. \n생각보다 일은 빨리 끝났다.",
    "choices": [
      { "text": "아무도 퇴근을 막을 순 없다", "nextId": "T3" },
      { "text": "대충 마무리한다", "nextId": "T3" }
    ]
  },
  "T3": {
    "id": "T3",
    "text": "덜컹 \n불안한 소리가 유난히도 크게 창고에 울렸다. \n덜컹 \n다시 한 번 문을 열려고 했지만 요지부동이었다. \n오전에 인쇄부 직원들이 창고 문이 수시로 고장나서 고쳐야한다는 말이 떠올랐다.",
    "choices": [
      { "text": "CCTV를 향해 두 팔을 흔든다", "nextId": "T4" },
      { "text": "인쇄실로 향한다", "nextId": "T5" }
    ]
  },
  "T4": {
    "id": "T4",
    "text": "팔이 떨어져라 흔들었지만 아무도 보는 이가 없는지, \n창고로 오질 않았다.",
    "choices": [
      { "text": "잠시 쉰다", "nextId": "T6" },
      { "text": "근처에 주저앉는다", "nextId": "T6" }
    ]
  },
  "T5": {
    "id": "T5",
    "text": "기계 돌아가는 소리가 멈춘 인쇄실에도 정적이 흘렀다. \n문을 당겨봤지만 안쪽에서 잠궜는지, 열리지 않았다.",
    "statusChange": {
          "energy": "+100",
          "fire": "+0",
          "cold": "+0",
          "tired": "+10"
 },
    "choices": [
      { "text": "잠시 쉰다", "nextId": "T6" },
      { "text": "근처에 주저앉는다", "nextId": "T6" }
    ]
  },
  "T6": {
    "id": "T6",
    "text": "갈 곳 잃은 눈동자가 멍하니 천장을 올려다봤다. \n그러다가 뒤에서 느껴지는 시선에 돌아봤다. \n'저게 뭐지?' \n드럼통이었다. \n그것도 네 개씩이나 되는 드럼통이 창고의 한 가운데 덩그러니 모여 있었다. \n자세히 보니, 인쇄실에서 쓰는 20KG짜리 잉크였다. \n헛것을 보고 있다기엔 너무나도 생생한 존재감이 뿜어져나왔다. \n인쇄실에 있어야할 것이 창고에 있다니? \n믿기지 않는 현상에 고개를 갸웃거렸다. \n'정신이라도 나갔나?' \n자조적인 웃음이 절로 나왔다.",
    "choices": [
      { "text": "드럼통을 노려본다", "nextId": "T7" },
      { "text": "드럼통과 거리를 둔다", "nextId": "T7" }
    ]
  },
  "T7": {
    "id": "T7",
    "text": "얼마나 시간이 흘렀을까? \n갑자기 솟아난 드럼통과 대치한 지, 꽤 많은 시간이 흘렀다. \n휴대폰이 있다면 좋겠지만 아쉽게도 화장실에 두고 온 걸 뒤늦게 알았다. \n창고 문이 고장났으니 가져오는 것도 불가능 \n날이 어두워질수록 슬슬 한기가 들기 시작했다. \n아직은 겨울의 끝자락 \n굳게 닫힌 커다란 문틈으로 앙상한 칼바람이 새어들었다. \n'어쩌면 좋을까?'",
    "choices": [
      { "text": "바람 막을 것을 찾는다", "nextId": "C1" },
      { "text": "가볍게 몸을 움직인다", "nextId": "D1" },
      { "text": "주변을 둘러본다", "nextId": "F1" },
      { "text": "창문을 열려고 시도한다", "nextId": "E1" }
    ]
  },
  "C1": {
    "id": "C1",
    "text": "포장된 지류에서 비닐을 벗겨냈다. \n담요처럼 몸에 두르니, 한결 나아졌다. \n하지만 날이 더 어두워지자 몸이 덜덜 떨렸다. \n마치 옷을 걸치지 않고서 설원 한복판에 선 기분마저 들었다.",
    "statusChange": {
          "cold": "+30"
    },
    "choices": [
      { "text": "바람 피할 곳을 찾는다", "nextId": "C2" },
      { "text": "주위를 살펴본다", "nextId": "choice1" }
    ]
  },
  "C2": {
    "id": "C2",
    "text": "창고의 중간 \n그나마 팔레트가 벽처럼 사위를 둘러싼 곳에 몸을 웅크렸다. \n하지만, \n매서운 바람이 피부를 사정이 물어뜯었다. \n너무 추워 손끝이 마비될 것만 같았다. \n..... \n아무리 생각해도 이런 추위는 말이 되지 않는다. \n머리가 이상해져버린 걸까?",
   "statusChange": {
          "cold": "+30"
   },
    "choices": [
      { "text": "지류의 포장을 전부 뜯는다", "nextId": "C3" },
      { "text": "이대로는 안 된다", "nextId": "choice1" }
    ]
  },
  "C3": {
    "id": "C3",
    "text": "지류를 감싸던 포장지, 팔레트를 덮고 있던 비닐 그리고 새하얀 종이까지 죄다 끌어모아 덮었다. \n강박적으로 몸 위에다가 종이를 쌓고 \n쌓고 \n 쌓고 \n 또 \n쌓았다. \n그럼에도 한기가 목구멍까지 들어왔다. \n이건 이상해도 너무 이상했다. \n냉동창고로 변해버린 것마냥 웅크린 채로 움직일 수조차도 없게 되었다. \n'나는...'",
   "statusChange": {
          "cold": "+30"
   },
    "choices": [
      { "text": "그래도 버텨본다", "nextId": "C4" },
      { "text": "자리를 박차고 나간다", "nextId": "choice1" }
    ]
  },
  "C4": {
    "id": "C4",
    "text": "마스크 안에서 맴돌던 입김이 얼었다. \n무언가 잘못되어도 단단히 잘못되었음을 직감했지만 이미 늦었다. \n몸은 굳었고 목소리도 나오질 않았다. \n점점 흐려지는 의식 속에서 청색의 드럼통이 눈앞에 보였다. \n'저 속은 따뜻할까?'",
   "statusChange": {
          "cold": "+30"
   },
    "choices": [
      { "text": "몸이 이끄는대로 한다.", "nextId": "" }
    ]
  },
  "badEndingC": {
    "id": "badEndingC",
    "text": "<작업지시서> \n재작업, 인쇄 뒷묻음 주의",
    "choices": []
  },
  "choice1": {
    "id": "choice1",
    "text": "눈에 띈 것은",
   "statusChange": {
          "cold": "=0"
   },
    "choices": [
      { "text": "없다", "nextId": "D1" },
      { "text": "빈 깡통이다", "nextId": "F1" },
      { "text": "창문이다", "nextId": "E1" }
    ]
  },
  "D1": {
    "id": "D1",
    "text": "창고 안을 돌아다니고 또 돌아다녀봤지만 쓸만한 건 없었다. \n아까부터 드는 추위에 몸을 쉬지 않고 움직였다.",
   "statusChange": {
          "tired": "+50"
   }, 
    "choices": [
      { "text": "가볍게 통통 뛰어오른다", "nextId": "D2" },
      { "text": "쓸데없으니 그만둔다", "nextId": "choice2" }
    ]
  },
  "D2": {
    "id": "D2",
    "text": "문득 졸리다는 생각이 들었다. \n졸리다? \n쉴새없이 움직이는 몸뚱이라는 아이러니하게도 수면을 요구하고 있었다. \n탁 \n발이 지면에 맞닿았다. \n몸이 멈추자 지독한 졸음이 몰려들기 시작했다. \n점점 흐려지는 의식 속에서 황색의 드럼통이 눈앞에 보였다. \n'저 속은 포근할까?'",
   "statusChange": {
          "tired": "+50"
   },
    "choices": [
      { "text": "몸이 이끄는대로 한다.", "nextId": "" }
    ]
  },
 "badEndingD": {
    "id": "badEndingD",
    "text": "<작업지시서> \n긴급, 금일 야간 인쇄",
    "choices": []
  },
 "choice2": {
    "id": "choice2",
    "text": "눈에 띈 것은",
   "statusChange": {
          "tired": "=10"
   },
    "choices": [
      { "text": "창고에 널린 포장재다", "nextId": "C1" },
      { "text": "빈 깡통이다", "nextId": "F1" },
      { "text": "창문이다", "nextId": "E1" }
    ]
  },
  "F1": {
    "id": "F1",
    "text": "은색의 찬란함을 빛내는 저 깡통은 알콜이라고 들었다. \n다 쓴 직사면체의 알콜 캔을 저렇게 쌓아뒀다가 한 번에 처리한다. \n그렇다라는 건, 저 속에 얼마라도 남은 것은 알콜이란 소리다. \n음료 캔도 다 마셨다고 쳐도 아주 작은 한 방울정도는 남아있는 법 \n주머니에서 느껴지는 라이터의 감촉에 세상을 다 가진 기분이었다.",
   "statusChange": {
          "fire": "+20"
   },
    "choices": [
      { "text": "알콜을 모은다", "nextId": "F2" },
      { "text": "자칫 불이 날 수 있다", "nextId": "choice3" }
    ]
  },
  "F2": {
    "id": "F2",
    "text": "얼마 전에 본 다큐에서 인테리어를 하는 작업자가 \n바닥을 건조시키기 위해서 알콜 깡통에다가 불을 피워둔 것을 본 적이 있다. \n알콜이 다 타면 불은 저절로 꺼질 것이고 불이 번질 염려도 없다. \n이윽고 깡통의 입구에 돌돌 말아넣은 심지가 활활 타올랐다.",
   "statusChange": {
          "fire": "+30"
   },
    "choices": [
      { "text": "따뜻하다", "nextId": "F3" },
      { "text": "이건 미친 짓이다", "nextId": "choice3" }
    ]
  },
  "F3": {
    "id": "F3",
    "text": "비록 뚜껑을 완전히 열지는 못했지만 열기를 품은 깡통은 따뜻했다. \n하지만 \n뭔가가 \n뭔가가 아쉬었다.",
   "statusChange": {
          "fire": "+40"
   },
    "choices": [
      { "text": "태울 것이 더 필요하다", "nextId": "F4" },
      { "text": "그만둔다", "nextId": "choice3" }
    ]
  },
  "F4": {
    "id": "F4",
    "text": "홀린듯이 발걸음을 뗐다. \n창고에는 오늘 밤을 따뜻하게 보낼 장작들이 아주 많았다. \n어차피 밖에서 갇힌지 모른다면 연기를 피우는 것도 좋은 방법이다. \n한 손에는 종이뭉치를, \n다른 한 손에는 라이터를 켠 채로, \n적색의 드럼통 앞에 섰다. \n'여기도 태울 것이 있네?'",
   "statusChange": {
          "fire": "+50"
   },
    "choices": [
      { "text": "몸이 이끄는대로 한다.", "nextId": "" }
    ]
  },
 "badEndingF": {
    "id": "badEndingF",
    "text": "<작업지시서> \n충분히 건조시킬 것",
    "choices": []
  },
  "choice3": {
    "id": "choice3",
    "text": "눈에 띈 것은",
   "statusChange": {
          "fire": "=0"
   },
    "choices": [
      { "text": "없다", "nextId": "D1" },
      { "text": "창고에 널린 포장재다", "nextId": "C1" },
      { "text": "창문이다", "nextId": "E1" }
    ]
  },
  "E1": {
    "id": "E1",
    "text": "창고의 가장 후미진 곳 \n거기엔 외부가 보이는 창문이 있었다. \n왜 진즉에 생각치 못했을까? \n창고 가운데를 독차지한 드럼통을 피해 창문으로 다가갔다.",
    "choices": [
      { "text": "창문을 열어본다", "nextId": "E2" },
      { "text": "괜한 힘 낭비다", "nextId": "choice4" }
    ]
  },
  "E3": {
    "id": "E3",
    "text": "힘으로 밀어봤지만 어째선지 꿈쩍도 않는 창문이었다. \n딱히 잠금장치가 걸린 것도 아닌데 힘을 주어 밀어봤지만 헛수고였다. \n드럼통도 그렇고 창문도 그렇고 생각할수록 이상한 점이 한 둘이 아니었다. \n닭살이 돋을 만큼 등골이 서늘해졌고 어서 여길 빠져나가고 싶단 마음뿐이었다. \n다급함에 돌아가는 시선이 지게차에서 멎었다.",
   "statusChange": {
          "energy": "-40"
   },
    "choices": [
      { "text": "지게차에 시동을 건다", "nextId": "E4" },
      { "text": "심호흡을 한다", "nextId": "choice4" }
    ]
  },
  "E5": {
    "id": "E5",
    "text": "콰앙! \n굉음과 함께 걸리적거리던 드럼통이 바닥을 나뒹굴었다. \n안에 있던 잉크가 사방팔방으로 비산하며, 흰 종이가 제각기 색으로 물들어갔다. \n그 사이, 가속을 받은 지게차가 창고의 반대편 끝까지 거의 다다랐다.",
   "statusChange": {
          "energy": "-40"
   },
    "choices": [
      { "text": "계속 악셀을 밝는다", "nextId": "E6" },
      { "text": "악셀에서 발을 뗀다", "nextId": "choice4" }
    ]
  },
  "E6": {
    "id": "E6",
    "text": "'어?' \n부딪칠 것이란 예상과 다르게 지게차의 지게날에 찔린 창문은 멀쩡했다. \n오히려 창문에서 더욱 멀어졌다. \n오른발은 연신 악셀을 눌렀지만 허공을 누르는 느낌이었고 \n조향을 조작하던 오른손에는 끈적함이 가득했다. \n더는 추위가 느껴지지 않는다고 느껴질 무렵, \n눈이 동그랗게 떠졌다. \n'으악!' \n'이게 뭐야!' \n정신을 차렸을 때는 이미 바닥과 몸이 붙어버린 뒤였다. \n아니, 정확하게는 \n방금 전 지게차가 치고 간 드럼통에서 흘러나온 잉크가 \n접착제처럼 몸을 붙들어 집어삼키고 있었다. \n'안!...풉...푸흡...' \n머리가 반쯤 삼켜지자 입 안으로 잉크가 흘러들어왔다.",
   "statusChange": {
          "energy": "-40"
   },
    "choices": [
      { "text": "발버둥친다", "nextId": "" },
      { "text": "현실을 받아들인다", "nextId": "" }
    ]
  },
 "badEndingE": {
    "id": "badEndingE",
    "text": "..... \n..... \n..... \n13관리부 제3과에서의 보고입니다 \n이번에 3C-CMYK로 명명된 개체는 비정형체으로 판명되었으며, 제거 단계로의 이행이 어려운 점을 고려하여 사업장의 폐쇄를 결정했습니다. \n이후, 3C-CMYK는 확인 단계에서 주시 단계로 조정했습니다. \n이 개체는 잉크에 기생하는 형태로 주로 잉크가 지나다니는 관에 서식하고 있다가 주변에 있는 인간을 납치하여 재료로 사용하는 것으로 확인되었습니다. \n비이상적으로 <작업지시서>라는 것에 집착을 가지고 있고 이를 위해 다른 사물을 이용하다가 우연히 인간을 재료로 사용한 것이 시작인 것 같습니다만 첫 실종 사건과 시기가 맞지 않아 좀 더 조사가 필요합니다. \n이번 실종 사건에 사용된 <작업지시서>를 함께 첨부합니다. <작업지시서> \n주의, 색상 맞출것, 선명하게",
    "choices": []
  },
"choice4": {
    "id": "choice4",
    "text": "눈에 띈 것은",
   "statusChange": {
          "energy": "=100"
   },
    "choices": [
      { "text": "없다", "nextId": "D1" },
      { "text": "창고에 널린 포장재다", "nextId": "C1" },
      { "text": "빈 깡통이다", "nextId": "F1" }
    ]
  }

}